MANIFEST.in
README.rst
setup.py
docs/HISTORY.txt
docs/INSTALL.txt
docs/LICENSE.GPL
docs/LICENSE.txt
docs/TODO.txt
unice/.DS_Store
unice/__init__.py
unice.portlet.mot.egg-info/PKG-INFO
unice.portlet.mot.egg-info/SOURCES.txt
unice.portlet.mot.egg-info/dependency_links.txt
unice.portlet.mot.egg-info/entry_points.txt
unice.portlet.mot.egg-info/namespace_packages.txt
unice.portlet.mot.egg-info/not-zip-safe
unice.portlet.mot.egg-info/requires.txt
unice.portlet.mot.egg-info/top_level.txt
unice/portlet/.DS_Store
unice/portlet/__init__.py
unice/portlet/mot/.DS_Store
unice/portlet/mot/__init__.py
unice/portlet/mot/configure.zcml
unice/portlet/mot/motportlet.pt
unice/portlet/mot/motportlet.py
unice/portlet/mot/vocabularies.py
unice/portlet/mot/browser/.DS_Store
unice/portlet/mot/browser/__init__.py
unice/portlet/mot/browser/configure.zcml
unice/portlet/mot/browser/stylesheets/styles.css
unice/portlet/mot/profiles/.DS_Store
unice/portlet/mot/profiles/default/cssregistry.xml
unice/portlet/mot/profiles/default/metadata.xml
unice/portlet/mot/profiles/default/portlets.xml
unice/portlet/mot/tests/__init__.py
unice/portlet/mot/tests/base.py
unice/portlet/mot/tests/test_portlet.py